ccpem_utils/__init__.py
ccpem_utils/image/__init__.py
ccpem_utils/map/__init__.py
ccpem_utils/map/array_utils.py
ccpem_utils/map/mrc_map_utils.py
ccpem_utils/map/mrcfile_utils.py
ccpem_utils/map/parse_mrcmapobj.py
ccpem_utils/model/__init__.py
ccpem_utils/model/coord_grid.py
ccpem_utils/model/gemmi_model_utils.py
ccpem_utils/model/model_utils.py
ccpem_utils/other/__init__.py
ccpem_utils/other/calc.py
ccpem_utils/other/cluster.py
ccpem_utils/other/json_utils.py
ccpem_utils/other/utils.py
ccpem_utils/other/wrappers.py
ccpem_utils/scripts/__init__.py
ccpem_utils/scripts/add_softedge_map.py
ccpem_utils/scripts/analyse_bfactors.py
ccpem_utils/scripts/crop_pad_map.py
ccpem_utils/scripts/downsample_map.py
ccpem_utils/scripts/edit_map_origin_nstart.py
ccpem_utils/scripts/generate_contour_mask.py
ccpem_utils/scripts/get_contacts.py
ccpem_utils/scripts/get_map_bfactor.py
ccpem_utils/scripts/get_map_parameters.py
ccpem_utils/scripts/lowpass_filter.py
ccpem_utils/scripts/set_sigf_fom_columns.py
ccpem_utils/scripts/shift_model_back_origin_nonzero.py
ccpem_utils/scripts/shift_model_refmap_origin.py
ccpem_utils/sequence/__init__.py
ccpem_utils/sequence/sequence_utils.py
ccpem_utils-0.0.1.dev34.dist-info/licenses/LICENSE
ccpem_utils_tests/__init__.py
ccpem_utils_tests/test_calc.py
ccpem_utils_tests/test_cluster.py
ccpem_utils_tests/test_coord_grid.py
ccpem_utils_tests/test_gemmi_model_utils.py
ccpem_utils_tests/test_map_parse.py
ccpem_utils_tests/test_mrc_map_utils.py
ccpem_utils_tests/test_mrcfile_array_utils_gpu.py
ccpem_utils_tests/test_mrcfile_utils.py
ccpem_utils_tests/test_sequence_utils.py
ccpem_utils_tests/test_utils.py
ccpem_utils_tests/test_data/1ake_molmap45.mrc
ccpem_utils_tests/test_data/1ake_molmap45_tanhlp_eman2.mrc
ccpem_utils_tests/test_data/5me2.pdb
ccpem_utils_tests/test_data/5ni1_entry.fasta
ccpem_utils_tests/test_data/5ni1_updated.cif
ccpem_utils_tests/test_data/6vyb_Ndom.pdb
ccpem_utils_tests/test_data/6vyb_Ndom_shifted.pdb
ccpem_utils_tests/test_data/__init__.py
ccpem_utils_tests/test_data/__init__.pyc
ccpem_utils-0.0.1.dev34.dist-info/METADATA
ccpem_utils-0.0.1.dev34.dist-info/WHEEL
ccpem_utils-0.0.1.dev34.dist-info/top_level.txt
ccpem_utils-0.0.1.dev34.dist-info/RECORD
