Metadata-Version: 2.4
Name: ccpem_utils
Version: 0.0.1.dev34
Summary: "Python utils for EM data processing (dev version)"
Home-page: https://gitlab.com/ccpem/ccpem-utils
Classifier: Programming Language :: Python :: 3
Requires-Python: >=3.9
License-File: LICENSE
Requires-Dist: gemmi==0.7.4
Requires-Dist: numpy>=2.0.2
Requires-Dist: mrcfile
Requires-Dist: Pillow>=11.3.0
Requires-Dist: scipy>=1.13.1
Requires-Dist: pandas
Requires-Dist: scikit-learn>=1.6.1
Dynamic: license-file
